albumentations_experimental/__init__.py
albumentations_experimental/augmentations/__init__.py
albumentations_experimental/augmentations/keypoint_utils.py
albumentations_experimental/augmentations/transforms.py
albumentations_experimental-0.0.1.dist-info/LICENSE
albumentations_experimental-0.0.1.dist-info/METADATA
albumentations_experimental-0.0.1.dist-info/WHEEL
albumentations_experimental-0.0.1.dist-info/top_level.txt
albumentations_experimental-0.0.1.dist-info/RECORD
