Metadata-Version: 2.1
Name: albumentations-experimental
Version: 0.0.1
Summary: Experimental functionality for the Albumentaions library.
Home-page: https://github.com/albumentations-team/albumentations_experimental
Author: Buslaev Alexander, Alexander Parinov, Vladimir Iglovikov, Eugene Khvedchenya, Druzhinin Mikhail
License: MIT
Platform: UNKNOWN
Classifier: Development Status :: 4 - Beta
Classifier: License :: OSI Approved :: MIT License
Classifier: Intended Audience :: Developers
Classifier: Intended Audience :: Science/Research
Classifier: Operating System :: OS Independent
Classifier: Programming Language :: Python
Classifier: Programming Language :: Python :: 3
Classifier: Programming Language :: Python :: 3.5
Classifier: Programming Language :: Python :: 3.6
Classifier: Programming Language :: Python :: 3.7
Classifier: Programming Language :: Python :: 3.8
Classifier: Topic :: Software Development :: Libraries
Classifier: Topic :: Software Development :: Libraries :: Python Modules
Requires-Python: >=3.5
Requires-Dist: albumentations
Provides-Extra: tests
Requires-Dist: pytest ; extra == 'tests'
